CHANGES.rst
README.rst
setup.cfg
setup.py
kotti_docs_theme/__init__.py
kotti_docs_theme.egg-info/PKG-INFO
kotti_docs_theme.egg-info/SOURCES.txt
kotti_docs_theme.egg-info/dependency_links.txt
kotti_docs_theme.egg-info/not-zip-safe
kotti_docs_theme.egg-info/requires.txt
kotti_docs_theme.egg-info/top_level.txt
kotti_docs_theme/themes/kotti_docs_theme/bootstrap.js
kotti_docs_theme/themes/kotti_docs_theme/bootstrap.min.js
kotti_docs_theme/themes/kotti_docs_theme/layout.html
kotti_docs_theme/themes/kotti_docs_theme/localtoc.html
kotti_docs_theme/themes/kotti_docs_theme/relations.html
kotti_docs_theme/themes/kotti_docs_theme/theme.conf
kotti_docs_theme/themes/kotti_docs_theme/static/bootstrap-default.css
kotti_docs_theme/themes/kotti_docs_theme/static/bootstrap-default.min.css
kotti_docs_theme/themes/kotti_docs_theme/static/bootstrap-dropdown.js
kotti_docs_theme/themes/kotti_docs_theme/static/bootstrap-engineauth.css
kotti_docs_theme/themes/kotti_docs_theme/static/bootstrap-engineauth.min.css
kotti_docs_theme/themes/kotti_docs_theme/static/bootstrap-responsive.css
kotti_docs_theme/themes/kotti_docs_theme/static/bootstrap-responsive.min.css
kotti_docs_theme/themes/kotti_docs_theme/static/bootstrap-sapling.css
kotti_docs_theme/themes/kotti_docs_theme/static/jquery.js
kotti_docs_theme/themes/kotti_docs_theme/static/sphinx-bootstrap.css