Metadata-Version: 1.0
Name: kotti-docs-theme
Version: 0.2
Summary: Sphinx Theme for Kotti Documentation
Home-page: https://github.com/Kotti/kotti_docs_theme
Author: Andreas Kaiser
Author-email: disko@binary-punks.com
License: BSD
Keywords: sphinx theme kotti twitter bootstrap
Platform: UNKNOWN
Classifier: License :: OSI Approved :: BSD License
Classifier: Natural Language :: English
Classifier: Programming Language :: Python
Classifier: Topic :: Documentation
Classifier: Topic :: Software Development :: Documentation
